wquant/__init__.py
wquant/calc/__init__.py
wquant/calc/factor.py
wquant/calc/portfolio.py
wquant/db/__init__.py
wquant/db/orm.py
wquant-1.0.3.dist-info/LICENSE
wquant-1.0.3.dist-info/METADATA
wquant-1.0.3.dist-info/WHEEL
wquant-1.0.3.dist-info/top_level.txt
wquant-1.0.3.dist-info/RECORD
